MANIFEST.in
README.rst
requirements.txt
setup.py
zalando.egg-info/PKG-INFO
zalando.egg-info/SOURCES.txt
zalando.egg-info/dependency_links.txt
zalando.egg-info/entry_points.txt
zalando.egg-info/requires.txt
zalando.egg-info/top_level.txt
zalando_cli/__init__.py
zalando_cli/__main__.py
zalando_cli/main.py